pyvsbsdl.cpython-39-darwin.so
libvsbsdl_python-20240504.dist-info/METADATA
libvsbsdl_python-20240504.dist-info/WHEEL
libvsbsdl_python-20240504.dist-info/top_level.txt
libvsbsdl_python-20240504.dist-info/RECORD
